[
  {
    "timestamp": 1777992040.9687703,
    "input": "selam",
    "intent": "GREETING",
    "confidence": 0.7,
    "response": "Merhabalar, seni dinliyorum."
  },
  {
    "timestamp": 1777992042.6356277,
    "input": "adın ne",
    "intent": "IDENTITY",
    "confidence": 0.9,
    "response": "Ben Mergen. Türkçe A1 seviyesinde kelimeler bilen, dosyaları okuyup öğrenebilen bir dijital beyinim."
  },
  {
    "timestamp": 1777992044.6893787,
    "input": "nasılsın",
    "intent": "GREETING",
    "confidence": 0.6,
    "response": "Merhaba! Sana nasıl yardımcı olabilirim?"
  },
  {
    "timestamp": 1777992048.504172,
    "input": "ayak",
    "intent": "UNKNOWN",
    "confidence": 0.1,
    "response": "Ayak Türkçe'de bir isimdir. Bunu şöyle de söyleyebilirim: ayak önemli. Bunu şöyle de söyleyebilirim: Günlük hayatta ayak kullanılır."
  },
  {
    "timestamp": 1777992050.8528996,
    "input": "kar",
    "intent": "UNKNOWN",
    "confidence": 0.1,
    "response": "Kar bir isimdir. Bu kar güzel. Ayrıca, Masada bir kar var."
  },
  {
    "timestamp": 1777992054.6569586,
    "input": "kayra",
    "intent": "UNKNOWN",
    "confidence": 0.1,
    "response": "Bu konu hakkında bilgim yok. \"oku:dosya.txt\" ile bana öğretebilirsin."
  }
]